flask_mysqlpool/__init__.py
flask_mysqlpool-1.0.5.dist-info/LICENSE
flask_mysqlpool-1.0.5.dist-info/METADATA
flask_mysqlpool-1.0.5.dist-info/WHEEL
flask_mysqlpool-1.0.5.dist-info/top_level.txt
flask_mysqlpool-1.0.5.dist-info/RECORD
