Metadata-Version: 2.1
Name: flask_mysqlpool
Version: 1.0.5
Summary: Wrapper for mysql.connector.python to get a pool of mysql connections
Home-page: https://github.com/dthorell/mysqlpool
Author: Daniel Thorell
Author-email: dthorell@outlook.com
License: MIT
Platform: UNKNOWN
Classifier: License :: OSI Approved :: MIT License
Classifier: Programming Language :: Python
Classifier: Programming Language :: Python :: 3
Classifier: Programming Language :: Python :: 3.6
Classifier: Programming Language :: Python :: 3.7
Classifier: Programming Language :: Python :: Implementation :: CPython
Classifier: Operating System :: OS Independent
License-File: LICENSE
